{
  "app-users": [
    {
      "id": "1dcd",
      "username": "Damon",
      "password": "pass"
    },
    {
      "id": "971c",
      "username": "test2",
      "password": "pass"
    }
  ],
  "workouts": [
    {
      "id": "96ac",
      "workout": "Chest",
      "userID": "1dcd",
      "day": "Monday"
    },
    {
      "id": "929a",
      "workout": "Back",
      "userID": "1dcd",
      "day": "Tuesday"
    },
    {
      "id": "89ca",
      "workout": "Arms",
      "userID": "1dcd",
      "day": "Wednesday"
    },
    {
      "id": "f630",
      "workout": "Test",
      "userID": "1dcd",
      "day": "Saturday"
    }
  ]
}